{"chunk_definitions":[{"row":44,"row_count":1,"visible":true,"expansion_state":0,"options":{"engine":"r","label":"01"},"document_id":"50C8F25D","chunk_id":"c3wr9cx2o8qb0","chunk_label":"01"},{"row":76,"row_count":1,"visible":true,"expansion_state":0,"options":{"engine":"r","label":"02"},"document_id":"50C8F25D","chunk_id":"ct6ouikxhtuzm","chunk_label":"02"},{"row":97,"row_count":1,"visible":true,"expansion_state":0,"options":{"engine":"r","label":"02b"},"document_id":"50C8F25D","chunk_id":"c0std7snmjw6u","chunk_label":"02b"},{"row":119,"row_count":1,"visible":true,"expansion_state":0,"options":{"engine":"r","label":"03"},"document_id":"50C8F25D","chunk_id":"crtbwfdn6l3l7","chunk_label":"03"},{"row":137,"row_count":1,"visible":true,"expansion_state":0,"options":{"engine":"r","label":"05"},"document_id":"50C8F25D","chunk_id":"cme2zpake51k8","chunk_label":"05"},{"row":174,"row_count":1,"visible":true,"expansion_state":0,"options":{"tab.id":"bookmark_id","tbl-cap":"Les collocations principales","engine":"r","label":"06"},"document_id":"50C8F25D","chunk_id":"cg99qgyex7sqm","chunk_label":"06"},{"row":216,"row_count":1,"visible":true,"expansion_state":0,"options":{"engine":"r","label":"06b"},"document_id":"50C8F25D","chunk_id":"c6xrs2qp2zm1l","chunk_label":"06b"},{"row":255,"row_count":1,"visible":true,"expansion_state":0,"options":{"engine":"r","label":"07"},"document_id":"50C8F25D","chunk_id":"cp25x39ot5ncu","chunk_label":"07"},{"row":327,"row_count":1,"visible":true,"expansion_state":0,"options":{"engine":"r","label":"08"},"document_id":"50C8F25D","chunk_id":"clihrgnwruek3","chunk_label":"08"},{"row":397,"row_count":1,"visible":true,"expansion_state":0,"options":{"engine":"r","label":"09a"},"document_id":"50C8F25D","chunk_id":"cc1mtfkvnta6x","chunk_label":"09a"},{"row":414,"row_count":1,"visible":true,"expansion_state":0,"options":{"engine":"r","label":"09b"},"document_id":"50C8F25D","chunk_id":"cwchk5z6b8agq","chunk_label":"09b"},{"row":434,"row_count":1,"visible":true,"expansion_state":0,"options":{"engine":"r","label":"09c"},"document_id":"50C8F25D","chunk_id":"cevyf3lst8rki","chunk_label":"09c"},{"row":460,"row_count":1,"visible":true,"expansion_state":0,"options":{"engine":"r","label":"09d"},"document_id":"50C8F25D","chunk_id":"ceicec4iytfo9","chunk_label":"09d"},{"row":562,"row_count":1,"visible":true,"expansion_state":0,"options":{"engine":"r","label":"10a"},"document_id":"50C8F25D","chunk_id":"cq2eyh695mrkc","chunk_label":"10a"},{"row":580,"row_count":1,"visible":true,"expansion_state":0,"options":{"engine":"r","label":"10b"},"document_id":"50C8F25D","chunk_id":"cpc87zt7xwpmt","chunk_label":"10b"},{"row":601,"row_count":1,"visible":true,"expansion_state":0,"options":{"engine":"r","label":"10c"},"document_id":"50C8F25D","chunk_id":"c136petn59r0r","chunk_label":"10c"},{"row":624,"row_count":1,"visible":true,"expansion_state":0,"options":{"engine":"r","label":"10d"},"document_id":"50C8F25D","chunk_id":"cyn0emz47ohoc","chunk_label":"10d"},{"row":718,"row_count":1,"visible":true,"expansion_state":0,"options":{"engine":"r","label":"11a"},"document_id":"50C8F25D","chunk_id":"cmb5hzmqnzbfb","chunk_label":"11a"},{"row":736,"row_count":1,"visible":true,"expansion_state":0,"options":{"engine":"r","label":"11b"},"document_id":"50C8F25D","chunk_id":"cw4hwpdmu0l7u","chunk_label":"11b"},{"row":757,"row_count":1,"visible":true,"expansion_state":0,"options":{"engine":"r","label":"11c"},"document_id":"50C8F25D","chunk_id":"c0obuge9oubfj","chunk_label":"11c"},{"row":782,"row_count":1,"visible":true,"expansion_state":0,"options":{"engine":"r","label":"11d"},"document_id":"50C8F25D","chunk_id":"cbx4tog5fz4y0","chunk_label":"11d"},{"row":887,"row_count":1,"visible":true,"expansion_state":0,"options":{"engine":"r","label":"12a"},"document_id":"50C8F25D","chunk_id":"c49utmcgtg6cb","chunk_label":"12a"},{"row":905,"row_count":1,"visible":true,"expansion_state":0,"options":{"engine":"r","label":"12b"},"document_id":"50C8F25D","chunk_id":"cqmockcqwyfnp","chunk_label":"12b"},{"row":927,"row_count":1,"visible":true,"expansion_state":0,"options":{"engine":"r","label":"12c"},"document_id":"50C8F25D","chunk_id":"cghdtbtfgd5ku","chunk_label":"12c"},{"row":955,"row_count":1,"visible":true,"expansion_state":0,"options":{"engine":"r","label":"12d"},"document_id":"50C8F25D","chunk_id":"c18v09q5d3p88","chunk_label":"12d"},{"row":970,"row_count":1,"visible":true,"expansion_state":0,"options":{"engine":"r","label":"13"},"document_id":"50C8F25D","chunk_id":"cxf6k4ee6fqi7","chunk_label":"13"},{"row":1005,"row_count":1,"visible":true,"expansion_state":0,"options":{"engine":"r","label":"14"},"document_id":"50C8F25D","chunk_id":"ctodwssx1jia3","chunk_label":"14"},{"row":1060,"row_count":1,"visible":true,"expansion_state":0,"options":{"engine":"r","label":"15"},"document_id":"50C8F25D","chunk_id":"c2g1z45s4ld0n","chunk_label":"15"}],"doc_write_time":1687773251}